<?xml version="1.0" encoding="UTF-8" ?>
<bento xmlns="http://www.w3.org/1999/xhtml">
<head>
	<meta name="conversion-from" content="gapfill" />
	<meta name="conversion-date" content="2011-10-31" />
	<meta name="customised" content="true" />
	<link rel="stylesheet" href="../../css/questionBased.css" type="text/css" media="screen" />
<link rel="stylesheet" href="../../css/questionBased-print.css" type="text/css" media="print" />
	<style type="text/css">
	<![CDATA[
		/*
		 * List any exercise specific css here
		 */			
	]]>
	</style>
	
	
<script id="model" type="application/xml">
<popups>
    	<popup click="clickme" source="examtips" width="500" />
</popups>
<settings>
 	<param name="delayedMarking" value="true" />
</settings>
  <questions>
    <GapFillQuestion source="q1" block="b1">
      <answer value="whose" correct="true"/>
    </GapFillQuestion>
    <GapFillQuestion source="q2" block="b2">
      <answer value="which" correct="true"/>
    </GapFillQuestion>
    <GapFillQuestion source="q3" block="b3">
      <answer value="which" correct="true"/>
    </GapFillQuestion>
    <GapFillQuestion source="q4" block="b4">
      <answer value="which" correct="true"/>
    </GapFillQuestion>
    <GapFillQuestion source="q5" block="b5">
      <answer value="who" correct="true"/>
    </GapFillQuestion>
    <GapFillQuestion source="q6" block="b6">
      <answer value="whose" correct="true"/>
    </GapFillQuestion>
  </questions>
</script>

</head>
<body>
	
<header>
<div id="instruction">
	Relative clauses can be used to make one sentence from two. In each case below, complete the sentence by adding the relative pronoun.
</div>
</header>
	
<section id="body">
  <img class="rightFloat" src="../media/EN_AW_005.jpg" mode="1" id="1001"/><br/>
  <a id="clickme"><img class="imagetask" src="../media/btn_examtips.jpg" mode="1" id="1002"/></a>
<br/><br/><br/>
  <ol id="questionList">
  <li><span color="#7935AB">The water-balanced railway's hydraulic brake helps store energy to pump water. Its main function is to slow the train.</span>
  <br/> The water-balanced railway's hydraulic brake&#xA0;<input id="q1"/>&#xA0;main function is to slow the train, helps store energy to pump water.</li>
  <p class="linespace"></p>
  
  <li><span color="#7935AB">A solar cell is a power source. It converts sunlight into electricity.</span>
  <br/> A solar cell is a power source&#xA0;<input id="q2"/>&#xA0;converts sunlight into electricity.</li>
  <p class="linespace"></p>
  
  <li><span color="#7935AB">A hydram is powered by water pressure. It can irrigate fields 60 metres above the water source.</span>
  <br/> A hydram,&#xA0;<input id="q3"/>&#xA0;can irrigate fields sixty metres above the water source, is powered by water pressure.</li>
  <p class="linespace"></p>
  
  <li><span color="#7935AB">The water-balanced railway is an example of sustainable technology. It is powered by the force of gravity.</span>
  <br/> The water-balanced railway,&#xA0;<input id="q4"/>&#xA0;is powered by the force of gravity, is an example of sustainable technology.</li>
  <p class="linespace"></p>
  
  <li><span color="#7935AB">Ecologists are scientists. They study the relationship between living organisms and their environment.</span>
  <br/> Ecologists are scientists&#xA0;<input id="q5"/>&#xA0;study the relationship between living organisms and their environment.</li>
  <p class="linespace"></p>
  
  <li><span color="#7935AB">Greenpeace is an organisation. Its aim is to protect wildlife and the natural environment.</span>
  <br/> Greenpeace is an organisation&#xA0;<input id="q6"/>&#xA0;aim is to protect wildlife and the natural environment.</li>
  <p class="linespace"></p>
  
  </ol>
</section>

<section id="examtips">
<p class="popuptext">When describing an object we often use relative clauses to give information about its function, construction and so on. These may be defining relative clauses, for example:</p>
<p class="popuptext">A ballast tank is a tank which holds water for weight.</p>
<p class="popuptext">The relative clause gives essential information about the object, so it is a defining relative clause.</p>
<p class="popuptext">Or they may be non-defining relative clauses, for example:</p>
<p class="popuptext">The carriages, which can carry up to 20 passengers, go up and down a steep slope.</p>
<p class="popuptext">The relative clause gives additional information about the object, so it is a non-defining relative clause. Only non-defining relative clauses need to be enclosed in commas.</p>
</section>

</body>
</bento>