<?xml version="1.0" encoding="UTF-8" ?>
<bento xmlns="http://www.w3.org/1999/xhtml">
<head>
	<meta name="conversion-from" content="draganddrop" />
	<meta name="conversion-date" content="2012-01-16" />
	<meta name="customised" content="false" />
	<link rel="stylesheet" href="../../css/dropdown.css" type="text/css" media="screen" />
	<link rel="stylesheet" href="../../css/dropdown-print.css" type="text/css" media="print" />
	<style type="text/css">
	<![CDATA[
		/*
		 * List any exercise specific css here
		 */			
	]]>
	</style>
	<br/>
<script id="model" type="application/xml">
  <settings>
    <param name="delayedMarking" value="true"/>
  </settings>
  <questions>
  <DropDownQuestion source="q1" block="b1">
      <answer source="a1" correct="false"/>
      <answer source="a2" correct="false"/>
      <answer source="a3" correct="true"/>
	  <answer source="a4" correct="false"/>
	  <answer source="a5" correct="false"/>
    </DropDownQuestion>
    <DropDownQuestion source="q2" block="b2">
      <answer source="a6" correct="false"/>
      <answer source="a7" correct="true"/>
      <answer source="a8" correct="false"/>
	  <answer source="a9" correct="false"/>
	  <answer source="a10" correct="false"/>
    </DropDownQuestion>
    <DropDownQuestion source="q3" block="b3">
      <answer source="a11" correct="false"/>
      <answer source="a12" correct="false"/>
      <answer source="a13" correct="true"/>
	  <answer source="a14" correct="false"/>
	  <answer source="a15" correct="false"/>
    </DropDownQuestion>
    <DropDownQuestion source="q4" block="b4">
      <answer source="a16" correct="true"/>
      <answer source="a17" correct="false"/>
      <answer source="a18" correct="false"/>
	  <answer source="a19" correct="false"/>
	  <answer source="a20" correct="false"/>
    </DropDownQuestion>
    <DropDownQuestion source="q5" block="b5">
      <answer source="a21" correct="false"/>
      <answer source="a22" correct="true"/>
      <answer source="a23" correct="false"/>
	  <answer source="a24" correct="false"/>
	  <answer source="a25" correct="false"/>
    </DropDownQuestion>
    <DropDownQuestion source="q6" block="b6">
      <answer source="a26" correct="false"/>
      <answer source="a27" correct="false"/>
      <answer source="a28" correct="false"/>
	  <answer source="a29" correct="true"/>
	  <answer source="a30" correct="false"/>
    </DropDownQuestion>
    <DropDownQuestion source="q7" block="b7">
      <answer source="a31" correct="false"/>
      <answer source="a32" correct="true"/>
      <answer source="a33" correct="false"/>
	  <answer source="a34" correct="false"/>
	  <answer source="a35" correct="false"/>
    </DropDownQuestion>
    <DropDownQuestion source="q8" block="b8">
      <answer source="a36" correct="false"/>
      <answer source="a37" correct="false"/>
      <answer source="a38" correct="true"/>
	  <answer source="a39" correct="false"/>
	  <answer source="a40" correct="false"/>
    </DropDownQuestion>
    <DropDownQuestion source="q9" block="b9">
      <answer source="a41" correct="false"/>
      <answer source="a42" correct="false"/>
      <answer source="a43" correct="false"/>
	  <answer source="a44" correct="true"/>
	  <answer source="a45" correct="false"/>
    </DropDownQuestion>
    <DropDownQuestion source="q10" block="b10">
      <answer source="a46" correct="true"/>
      <answer source="a47" correct="false"/>
      <answer source="a48" correct="false"/>
	  <answer source="a49" correct="false"/>
	  <answer source="a50" correct="false"/>
    </DropDownQuestion>
    <DropDownQuestion source="q11" block="b11">
      <answer source="a51" correct="false"/>
      <answer source="a52" correct="true"/>
      <answer source="a53" correct="false"/>
	  <answer source="a54" correct="false"/>
	  <answer source="a55" correct="false"/>
    </DropDownQuestion>
    <DropDownQuestion source="q12" block="b12">
      <answer source="a56" correct="false"/>
      <answer source="a57" correct="false"/>
      <answer source="a58" correct="false"/>
	  <answer source="a59" correct="false"/>
	  <answer source="a60" correct="true"/>
    </DropDownQuestion>
    <DropDownQuestion source="q13" block="b13">
      <answer source="a61" correct="true"/>
      <answer source="a62" correct="false"/>
      <answer source="a63" correct="false"/>
	  <answer source="a64" correct="false"/>
	  <answer source="a65" correct="false"/>
    </DropDownQuestion>
    <DropDownQuestion source="q14" block="b14">
      <answer source="a66" correct="false"/>
      <answer source="a67" correct="false"/>
      <answer source="a68" correct="false"/>
	  <answer source="a69" correct="true"/>
	  <answer source="a70" correct="false"/>
    </DropDownQuestion>
    <DropDownQuestion source="q15" block="b15">
      <answer source="a71" correct="true"/>
      <answer source="a72" correct="false"/>
      <answer source="a73" correct="false"/>
	  <answer source="a74" correct="false"/>
	  <answer source="a75" correct="false"/>
    </DropDownQuestion>
    <DropDownQuestion source="q16" block="b16">
      <answer source="a76" correct="false"/>
      <answer source="a77" correct="false"/>
      <answer source="a78" correct="false"/>
	  <answer source="a79" correct="false"/>
	  <answer source="a80" correct="true"/>
    </DropDownQuestion>
    <DropDownQuestion source="q17" block="b17">
      <answer source="a81" correct="false"/>
      <answer source="a82" correct="false"/>
      <answer source="a83" correct="true"/>
	  <answer source="a84" correct="false"/>
	  <answer source="a85" correct="false"/>
    </DropDownQuestion>
    <DropDownQuestion source="q18" block="b18">
      <answer source="a86" correct="false"/>
      <answer source="a87" correct="false"/>
      <answer source="a88" correct="false"/>
	  <answer source="a89" correct="false"/>
	  <answer source="a90" correct="true"/>
    </DropDownQuestion>
    <DropDownQuestion source="q19" block="b19">
      <answer source="a91" correct="false"/>
      <answer source="a92" correct="false"/>
      <answer source="a93" correct="false"/>
	  <answer source="a94" correct="true"/>
	  <answer source="a95" correct="false"/>
    </DropDownQuestion>
    <DropDownQuestion source="q20" block="b20">
      <answer source="a96" correct="true"/>
      <answer source="a97" correct="false"/>
      <answer source="a98" correct="false"/>
	  <answer source="a99" correct="false"/>
	  <answer source="a100" correct="false"/>
    </DropDownQuestion>
    <DropDownQuestion source="q21" block="b21">
      <answer source="a101" correct="false"/>
      <answer source="a102" correct="false"/>
      <answer source="a103" correct="true"/>
	  <answer source="a104" correct="false"/>
	  <answer source="a105" correct="false"/>
    </DropDownQuestion>
    <DropDownQuestion source="q22" block="b22">
      <answer source="a106" correct="false"/>
      <answer source="a107" correct="true"/>
      <answer source="a108" correct="false"/>
	  <answer source="a109" correct="false"/>
	  <answer source="a110" correct="false"/>
    </DropDownQuestion>
    <DropDownQuestion source="q23" block="b23">
      <answer source="a111" correct="false"/>
      <answer source="a112" correct="false"/>
      <answer source="a113" correct="false"/>
	  <answer source="a114" correct="false"/>
	  <answer source="a115" correct="true"/>
    </DropDownQuestion>
    <DropDownQuestion source="q24" block="b24">
      <answer source="a116" correct="false"/>
      <answer source="a117" correct="false"/>
      <answer source="a118" correct="true"/>
	  <answer source="a119" correct="false"/>
	  <answer source="a120" correct="false"/>
    </DropDownQuestion>
  </questions>
</script>

</head>
<body>
	
<header>
<div id="instruction">Put the phrases into the correct group by dragging them across.</div>
</header>
	
<section id="body">
  <img class="rightFloat" src="../media/gt_set9.1_04.jpg" mode="1" id="1001"/>
  <div id="wrapper">

 <div id="part1">
	<ol>
		<li>I was wondering ...<tab/><tab/><tab/>
			<select id="q1">
					<option id="a1">giving advice</option>
					<option id="a2">linking expressions</option>
					<option id="a3">indirect questions / requests</option>
					<option id="a4">recommending</option>
					<option id="a5">apologising</option></select><br/></li>
		
		<li>As if this were not enough, ...<tab/><tab/>
			<select id="q2">
					<option id="a6">giving advice</option>
					<option id="a7">linking expressions</option>
					<option id="a8">indirect questions / requests</option>
					<option id="a9">recommending</option>
					<option id="a10">apologising</option></select><br/></li>
					
		<li>Could you let me know ...?<tab/><tab/>
			<select id="q3">
					<option id="a11">giving advice</option>
					<option id="a12">linking expressions</option>
					<option id="a13">indirect questions / requests</option>
					<option id="a14">recommending</option>
					<option id="a15">apologising</option></select><br/></li>
		
		<li>You ought to ...<tab/><tab/><tab/><tab/>
			<select id="q4">
					<option id="a16">giving advice</option>
					<option id="a17">linking expressions</option>
					<option id="a18">indirect questions / requests</option>
					<option id="a19">recommending</option>
					<option id="a20">apologising</option></select><br/></li>
					
		<li>To make matters even worse, ...<tab/>
			<select id="q5">
					<option id="a21">giving advice</option>
					<option id="a22">linking expressions</option>
					<option id="a23">indirect questions / requests</option>
					<option id="a24">recommending</option>
					<option id="a25">apologising</option></select><br/></li>
		
		<li>I know you'd really enjoy ...<tab/><tab/>
			<select id="q6">
					<option id="a26">giving advice</option>
					<option id="a27">linking expressions</option>
					<option id="a28">indirect questions / requests</option>
					<option id="a29">recommending</option>
					<option id="a30">apologising</option></select><br/></li>
					
		<li>To begin with, ...<tab/><tab/><tab/><tab/>
			<select id="q7">
					<option id="a31">giving advice</option>
					<option id="a32">linking expressions</option>
					<option id="a33">indirect questions / requests</option>
					<option id="a34">recommending</option>
					<option id="a35">apologising</option></select><br/></li>
					
		<li>Please let me know ...<tab/><tab/><tab/>
			<select id="q8">
					<option id="a36">giving advice</option>
					<option id="a37">linking expressions</option>
					<option id="a38">indirect questions / requests</option>
					<option id="a39">recommending</option>
					<option id="a40">apologising</option></select><br/></li>
					
		<li>You must see ...<tab/><tab/><tab/><tab/>
			<select id="q9">
					<option id="a41">giving advice</option>
					<option id="a42">linking expressions</option>
					<option id="a43">indirect questions / requests</option>
					<option id="a44">recommending</option>
					<option id="a45">apologising</option></select><br/></li>
					
		<li>I'd advise you to ...<tab/><tab/><tab/>
			<select id="q10">
					<option id="a46">giving advice</option>
					<option id="a47">linking expressions</option>
					<option id="a48">indirect questions / requests</option>
					<option id="a49">recommending</option>
					<option id="a50">apologising</option></select><br/></li>
					
		<li>Added to this, ...<tab/><tab/><tab/><tab/>
			<select id="q11">
					<option id="a51">giving advice</option>
					<option id="a52">linking expressions</option>
					<option id="a53">indirect questions / requests</option>
					<option id="a54">recommending</option>
					<option id="a55">apologising</option></select><br/></li>
					
		<li>Please accept my apologies for ...<tab/>
			<select id="q12">
					<option id="a56">giving advice</option>
					<option id="a57">linking expressions</option>
					<option id="a58">indirect questions / requests</option>
					<option id="a59">recommending</option>
					<option id="a60">apologising</option></select><br/></li>
					
		<li>If I were you, I'd ...<tab/><tab/><tab/>
			<select id="q13">
					<option id="a61">giving advice</option>
					<option id="a62">linking expressions</option>
					<option id="a63">indirect questions / requests</option>
					<option id="a64">recommending</option>
					<option id="a65">apologising</option></select><br/></li>
					
		<li>Do try and read ...<tab/><tab/><tab/>
			<select id="q14">
					<option id="a66">giving advice</option>
					<option id="a67">linking expressions</option>
					<option id="a68">indirect questions / requests</option>
					<option id="a69">recommending</option>
					<option id="a70">apologising</option></select><br/></li>
		
		<li>You'd better ...<tab/><tab/><tab/><tab/>
			<select id="q15">
					<option id="a71">giving advice</option>
					<option id="a72">linking expressions</option>
					<option id="a73">indirect questions / requests</option>
					<option id="a74">recommending</option>
					<option id="a75">apologising</option></select><br/></li>
		
		<li>I am terribly sorry but ...<tab/><tab/><tab/>
			<select id="q16">
					<option id="a76">giving advice</option>
					<option id="a77">linking expressions</option>
					<option id="a78">indirect questions / requests</option>
					<option id="a79">recommending</option>
					<option id="a80">apologising</option></select><br/></li>
					
		<li>I would be grateful if you could ...<tab/>
			<select id="q17">
					<option id="a81">giving advice</option>
					<option id="a82">linking expressions</option>
					<option id="a83">indirect questions / requests</option>
					<option id="a84">recommending</option>
					<option id="a85">apologising</option></select><br/></li>
					
		<li>I would like to apologise for ...<tab/><tab/>
			<select id="q18">
					<option id="a86">giving advice</option>
					<option id="a87">linking expressions</option>
					<option id="a88">indirect questions / requests</option>
					<option id="a89">recommending</option>
					<option id="a90">apologising</option></select><br/></li>
					
		<li>You'll absolutely love it!<tab/><tab/><tab/>
			<select id="q19">
					<option id="a91">giving advice</option>
					<option id="a92">linking expressions</option>
					<option id="a93">indirect questions / requests</option>
					<option id="a94">recommending</option>
					<option id="a95">apologising</option></select><br/></li>
					
		<li>I think you should ...<tab/><tab/><tab/>
			<select id="q20">
					<option id="a96">giving advice</option>
					<option id="a97">linking expressions</option>
					<option id="a98">indirect questions / requests</option>
					<option id="a99">recommending</option>
					<option id="a100">apologising</option></select><br/></li>
					
		<li>I would like to know ...<tab/><tab/><tab/>
			<select id="q21">
					<option id="a101">giving advice</option>
					<option id="a102">linking expressions</option>
					<option id="a103">indirect questions / requests</option>
					<option id="a104">recommending</option>
					<option id="a105">apologising</option></select><br/></li>
					
		<li>What is more, ...<tab/><tab/><tab/><tab/>
			<select id="q22">
					<option id="a106">giving advice</option>
					<option id="a107">linking expressions</option>
					<option id="a108">indirect questions / requests</option>
					<option id="a109">recommending</option>
					<option id="a110">apologising</option></select><br/></li>
					
		<li>Please forgive me for ...<tab/><tab/><tab/>
			<select id="q23">
					<option id="a111">giving advice</option>
					<option id="a112">linking expressions</option>
					<option id="a113">indirect questions / requests</option>
					<option id="a114">recommending</option>
					<option id="a115">apologising</option></select><br/></li>
					
		<li>Can you tell me ...?<tab/><tab/><tab/>
			<select id="q24">
					<option id="a116">giving advice</option>
					<option id="a117">linking expressions</option>
					<option id="a118">indirect questions / requests</option>
					<option id="a119">recommending</option>
					<option id="a120">apologising</option></select><br/></li>
		</ol>
<p class="linespace"></p>
		</div>
 </div>
</section>

</body>
</bento>