<?xml version="1.0" encoding="UTF-8"?>
<config>
	<id>/area1/RoadToIELTS2 ce.com</id>
	<productCode>52,53</productCode>
	<loginOption>128</loginOption>
	<dbHost>2</dbHost>
	<courseFile>menu-{productCode}-{productVersion}.xml</courseFile>
	<platform>tablet|Android</platform>
	<channel name='android-rackspace' caption='Ch1'>
		<streamingMedia>http://c284790.r90.stream.cf1.rackcdn.com/</streamingMedia>
	</channel>
	<channel name='vimeo' caption='Ch2'>
		<streamingMedia>http://player.vimeo.com/external/</streamingMedia>
	</channel>
	<sharedMedia />
	<brandingMedia />
	<language>EN</language>
	
	<!--  contentPath>http://www.clarityenglish.com/Content/</contentPath>
    <remoteDomain> http://www.clarityenglish.com/Software/</remoteDomain>
    <remoteGateway>http://www.clarityenglish.com/Software/ResultsManager/web/amfphp/</remoteGateway>-->
	
    <contentPath>http://www.clarityenglish.com/Content/</contentPath>
    <remoteDomain>http://www.clarityenglish.com/Software/</remoteDomain>
    <remoteGateway>http://www.clarityenglish.com/Software/ResultsManager/web/amfphp/</remoteGateway>
	
	<!--  contentPath>http://roadtoielts.chinaielts.org/Content/</contentPath>
    <remoteDomain>http://roadtoielts.chinaielts.org/Software/</remoteDomain>
    <remoteGateway>http://roadtoielts.chinaielts.org/Software/ResultsManager/web/amfphp/</remoteGateway>-->
	
	<remoteService>IELTSService</remoteService>
	<assetFolder>ResultsManager/web/resources/assets/</assetFolder>
	 
	<rememberLogin>true</rememberLogin>
	<disableAutoTimeout>true</disableAutoTimeout>
	
    <upgradeURL>http://www.ieltspractice.com</upgradeURL>
    <pricesURL>http://www.clarityenglish.com/enquiry.php?price=Road_to_IELTS_2</pricesURL>
    <registerURL>http://takeielts.britishcouncil.org/</registerURL>
    <getAccountURL>http://www.roadtoielts.com/</getAccountURL>
	
	<checkNetworkAvailabilityUrl>http://www.clarityenglish.com</checkNetworkAvailabilityUrl>
	<checkNetworkAvailabilityInterval>30</checkNetworkAvailabilityInterval>
	<checkNetworkAvailabilityReconnectInterval>5</checkNetworkAvailabilityReconnectInterval>
	
</config>