<?xml version="1.0" encoding="UTF-8" ?>
<bento xmlns="http://www.w3.org/1999/xhtml">
<head>
	<meta name="conversion" type="gapfill" date="2011-10-26" />
	<link rel="stylesheet" href="../../css/exercises.css" type="text/css" />
	<style type="text/css">
	<![CDATA[			
		list {
			list-style-type: decimal;
			margin-left: 0; 
			padding-left: 20px; 
			padding-bottom: 12px; 
		}
		p {
			padding-bottom: 12px; 
		}
		.no-padding {
			padding-bottom: 0px; 
		}
		.h1 {
			font-size: 12px;
			font-weight: bold;
			color: #3A00FF;	
		}
		#noscroll span[draggable="true"] {
		   float: left;
		   width: 140px;
		} 
	]]>
	</style>
	<script id="settings" type="application/xml">
		<settings>
		<marking/>
		<feedback wrongonly="false"/>
		<buttons/>
		<exercise/>
		<misc timed="243"/>
	</settings>
	</script>
	<br/>
<script id="model" type="application/xml">
<questions><GapFillQuestion source="q1"><answer value="do the homework " correct="true"/><answer value="do your homework" correct="true"/></GapFillQuestion><GapFillQuestion source="q2"><answer value="library " correct="true"/></GapFillQuestion><GapFillQuestion source="q3"><answer value="videos " correct="true"/><answer value="video cassettes" correct="true"/></GapFillQuestion><GapFillQuestion source="q4"><answer value="Make friends " correct="true"/><answer value="make friends" correct="true"/><answer value="Spend your time" correct="true"/><answer value="spend your time" correct="true"/><answer value="Spend some time" correct="true"/><answer value="spend some time" correct="true"/><answer value="Spend more time" correct="true"/><answer value="spend more time" correct="true"/></GapFillQuestion><GapFillQuestion source="q5"><answer value="conversation club " correct="true"/><answer value="English conversation club" correct="true"/></GapFillQuestion><GapFillQuestion source="q6"><answer value="list " correct="true"/><answer value="book list" correct="true"/></GapFillQuestion><GapFillQuestion source="q7"><answer value="Test yourself " correct="true"/><answer value="test yourself" correct="true"/></GapFillQuestion><GapFillQuestion source="q8"><answer value="news " correct="true"/><answer value="the news" correct="true"/></GapFillQuestion></questions></script>

</head>
<body>
	
<header>
	
		
		Listen to the recording, which will play automatically, and follow the instructions. Complete the notes below. Write NO MORE THAN THREE WORDS for each answer.
		
</header>
	
<section id="body">
	<img class="rightFloat" src="../Media/LC_LN_002.JPG" mode="1" id="1001"  /><media class="leftFloat" src="../Media/LC_LN1.mp3" mode="4" id="1002"  /><p align="left"><font color="#0000ff"><b>How to improve your English outside the classroom</b><font face="_sans" size="12" color="#000000">&#160;<font face="verdana" size="13" color="#0000ff"></font></font></font>- Make sure you (1) <input id="1" width="100" />.</p>- Make use of the (2) <input id="2" width="100" />.- Go to the cinema.- Watch television.- Borrow (3) <input id="3" width="100" />.- (4) <input id="4" width="100" /> with people of other nationalities.- Join clubs.- Start your own (5) <input id="5" width="100" />.<p align="left"><font color="#0000ff"><b>Dealing with problem areas</b>&#160;</font>Grammar&#160;- Select a book from the (6) <input id="6" width="100" />.</p>- Do grammar exercises regularly.<p align="left"><b>Vocabulary</b><font face="_sans" size="12">&#160;<font face="verdana" size="13"></font></font>- Select 5 new words a day.- Write them on cards.- (7) <input id="7" width="100" /> whenever you have time to kill.</p><p align="left"><b>Listening</b><font face="_sans" size="12">&#160;<font face="verdana" size="13"></font></font>- Tape (8) <input id="8" width="100" /> from the radio or TV.</p>- Take notes.- Listen again to check.<p align="left"><font size="2"></font></p>
</section>
<section id="fb1">
	<p align="left"><font color="#000000">1. The speaker says 'Firstly' followed by 'your homework! Please do it!'</font></p>
</section>
<section id="fb2">
	<p align="left">2. The speaker says 'Secondly, the library. Do make the most of it.'</p>
</section>
<section id="fb3">
	<p align="left">3. The speaker says 'take out videos' and 'take out' is similar in meaning to 'borrow'.</p>
</section>
<section id="fb4">
	<p align="left">4. You have to listen carefully after the speaker says 'Make friends' because the exact words are not given.</p>
</section>
<section id="fb5">
	<p align="left">5. The speaker says 'set up your own conversation club' and 'set up' has a similar meaning to 'start'.</p>
</section>
<section id="fb6">
	<p align="left">6. The speaker says 'choose one of the grammar books from the list' and 'choose' has a similar meaning to 'select'.</p>
</section>
<section id="fb7">
	<p align="left">7. The speaker says 'whenever you're travelling on a bus or sitting around waiting' which means the same as 'having time to kill', so you should have been prepared to hear his suggestion.</p>
</section>
<section id="fb8">
	<p align="left">8. The speaker says you can 'record' the news which means the same as 'tape' the news.</p>
</section>
</body>
</bento>